ebook_utils/__init__.py
ebook_utils/_version.py
ebook_utils/book.py
ebook_utils/main.py
ebook_utils/utils.py
ebook_utils-0.1.2.dist-info/METADATA
ebook_utils-0.1.2.dist-info/WHEEL
ebook_utils-0.1.2.dist-info/entry_points.txt
ebook_utils-0.1.2.dist-info/top_level.txt
ebook_utils-0.1.2.dist-info/RECORD
