Metadata-Version: 2.1
Name: ebook-utils
Version: 0.1.2
Summary: Simple ebook utility program
Home-page: https://gitlab.com/mikelplhts/ebook-utils
Author: Michele Lapolla
Author-email: Michele Lapolla <mikee.lapo@gmail.com>
Project-URL: Homepage, https://gitlab.com/mikelplhts/ebook-utils
Project-URL: Bug Tracker, https://gitlab.com/mikelplhts/ebook-utils/issues
Classifier: Development Status :: 1 - Planning
Classifier: Environment :: Console
Classifier: Intended Audience :: End Users/Desktop
Classifier: License :: OSI Approved :: GNU General Public License v3 (GPLv3)
Classifier: Natural Language :: English
Classifier: Programming Language :: Python
Classifier: Programming Language :: Python :: 3.8
Classifier: Programming Language :: Python :: 3.9
Classifier: Programming Language :: Python :: 3.10
Requires-Python: >=3.8
License-File: LICENSE
Requires-Dist: ebooklib (>=0.17.1)
Requires-Dist: beautifulsoup4 (>=4.11.1)
